fastdownload/__init__.py
fastdownload/_nbdev.py
fastdownload/core.py
fastdownload/download_checks.py
fastdownload/urls.py
fastdownload-0.0.7.dist-info/LICENSE
fastdownload-0.0.7.dist-info/METADATA
fastdownload-0.0.7.dist-info/WHEEL
fastdownload-0.0.7.dist-info/top_level.txt
fastdownload-0.0.7.dist-info/RECORD
